rstgen/__init__.py
rstgen/buildblog.py
rstgen/confparser.py
rstgen/utils.py
rstgen/sphinxconf/__init__.py
rstgen/sphinxconf/base.py
rstgen/sphinxconf/blog.py
rstgen/sphinxconf/complex_tables.py
rstgen/sphinxconf/default_conf.py
rstgen/sphinxconf/dirtables.py
rstgen/sphinxconf/insert_input.py
rstgen/sphinxconf/interproject.py
rstgen/sphinxconf/refstothis.py
rstgen/sphinxconf/select_lang.html
rstgen/sphinxconf/sigal_image.py
rstgen/sphinxconf/languages/__init__.py
rstgen/sphinxconf/languages/et.py
rstgen/sphinxconf/static/atelier.css
rstgen/sphinxconf/static/insipid-cust.css
rstgen/sphinxconf/templates/facebook-button.html
rstgen/sphinxconf/templates/home-button.html
rstgen/sphinxconf/templates/index-button.html
rstgen/sphinxconf/templates/languages-button.html
rstgen/sphinxconf/templates/languages.html
rstgen/sphinxconf/templates/layout.html
rstgen/sphinxconf/templates/links.html
rstgen/sphinxconf/templates/share-buttons.html
rstgen/sphinxconf/templates/show-source.html
rstgen/sphinxconf/templates/unused_layout.html
rstgen/sphinxconf/templates/dirtables/entry.rst
rstgen-25.9.0.dist-info/METADATA
rstgen-25.9.0.dist-info/WHEEL
rstgen-25.9.0.dist-info/licenses/COPYING
rstgen-25.9.0.dist-info/RECORD
